ncarrays/__init__.py
ncarrays/_coordinate_system.py
ncarrays/_geospatial_functions.py
ncarrays/_ncarrays.py
ncarrays/_post_processing.py
ncarrays/_variable_interpretation.py
ncarrays-0.0.8.dist-info/LICENSE
ncarrays-0.0.8.dist-info/METADATA
ncarrays-0.0.8.dist-info/WHEEL
ncarrays-0.0.8.dist-info/top_level.txt
ncarrays-0.0.8.dist-info/RECORD
