Metadata-Version: 2.1
Name: ncarrays
Version: 0.0.8
Summary: Subset netCDF arrays using OPeNDAP
Home-page: https://github.com/jenochjones/ncarrays
Author: J Enoch Jones
Author-email: jonenochjones@gmail.com
Classifier: Programming Language :: Python :: 3
Classifier: License :: OSI Approved :: MIT License
Classifier: Operating System :: OS Independent
License-File: LICENSE
